Metadata-Version: 1.1
Name: truths
Version: 1.0
Summary: auth generate truth tables
Home-page: https://github.com/tr3buchet/truths
Author: Trey Morris
Author-email: trey@treymorris.com
License: Apache Software License
Keywords: truth,table,truth table,truthtable,logic
Platform: UNKNOWN
Classifier: Development Status :: 5 - Production/Stable
Classifier: License :: OSI Approved :: Apache Software License
